MANIFEST.in
README.rst
setup.py
tests/__init__.py
tests/test_addr_view.py
tests/test_api_schema.py
tests/test_database.py
tests/test_file_logger.py
tests/test_firewall.py
tests/test_healthcheck.py
tests/test_log_sender.py
tests/test_portmap_view.py
tests/test_shell.py
tests/test_worker.py
uds_vlab_ipam_api/__init__.py
uds_vlab_ipam_api/app.ini
uds_vlab_ipam_api/app.py
uds_vlab_ipam_api/ddns_updater.py
uds_vlab_ipam_api/log_sender.py
uds_vlab_ipam_api/uds-vlab-ddns-updater.service
uds_vlab_ipam_api/uds-vlab-ipam.service
uds_vlab_ipam_api/uds-vlab-log-sender.service
uds_vlab_ipam_api/uds-vlab-worker.service
uds_vlab_ipam_api/version.py
uds_vlab_ipam_api/worker.py
uds_vlab_ipam_api.egg-info/PKG-INFO
uds_vlab_ipam_api.egg-info/SOURCES.txt
uds_vlab_ipam_api.egg-info/dependency_links.txt
uds_vlab_ipam_api.egg-info/requires.txt
uds_vlab_ipam_api.egg-info/top_level.txt
uds_vlab_ipam_api/lib/__init__.py
uds_vlab_ipam_api/lib/constants.py
uds_vlab_ipam_api/lib/database.py
uds_vlab_ipam_api/lib/exceptions.py
uds_vlab_ipam_api/lib/file_logger.py
uds_vlab_ipam_api/lib/firewall.py
uds_vlab_ipam_api/lib/shell.py
uds_vlab_ipam_api/lib/views/__init__.py
uds_vlab_ipam_api/lib/views/addr.py
uds_vlab_ipam_api/lib/views/healthcheck.py
uds_vlab_ipam_api/lib/views/portmap.py