Metadata-Version: 2.1
Name: uds-vlab-ipam-api
Version: 2.0.20220713
Summary: A RESTful API for automated IPAM of a personal lab in vLab
Author: UDS Tools
Author-email: uds.tools@dell.com
Classifier: Development Status :: 4 - Beta
Classifier: Intended Audience :: Developers
Classifier: License :: OSI Approved :: Apache Software License
Classifier: Natural Language :: English
Classifier: Operating System :: POSIX :: Linux
Classifier: Programming Language :: Python :: 3.6
